ome_types/__init__.py
ome_types/_conversion.py
ome_types/_pydantic_compat.py
ome_types/etree_fixes.py
ome_types/napari.yaml
ome_types/ome-2016-06.xsd
ome_types/py.typed
ome_types/units.py
ome_types/widget.py
ome_types/_autogenerated/__init__.py
ome_types/_autogenerated/ome_2016_06/__init__.py
ome_types/_autogenerated/ome_2016_06/affine_transform.py
ome_types/_autogenerated/ome_2016_06/annotation.py
ome_types/_autogenerated/ome_2016_06/annotation_ref.py
ome_types/_autogenerated/ome_2016_06/arc.py
ome_types/_autogenerated/ome_2016_06/arc_type.py
ome_types/_autogenerated/ome_2016_06/basic_annotation.py
ome_types/_autogenerated/ome_2016_06/bin_data.py
ome_types/_autogenerated/ome_2016_06/bin_data_compression.py
ome_types/_autogenerated/ome_2016_06/binary_file.py
ome_types/_autogenerated/ome_2016_06/binning.py
ome_types/_autogenerated/ome_2016_06/boolean_annotation.py
ome_types/_autogenerated/ome_2016_06/channel.py
ome_types/_autogenerated/ome_2016_06/channel_acquisition_mode.py
ome_types/_autogenerated/ome_2016_06/channel_contrast_method.py
ome_types/_autogenerated/ome_2016_06/channel_illumination_type.py
ome_types/_autogenerated/ome_2016_06/channel_ref.py
ome_types/_autogenerated/ome_2016_06/comment_annotation.py
ome_types/_autogenerated/ome_2016_06/dataset.py
ome_types/_autogenerated/ome_2016_06/dataset_ref.py
ome_types/_autogenerated/ome_2016_06/detector.py
ome_types/_autogenerated/ome_2016_06/detector_settings.py
ome_types/_autogenerated/ome_2016_06/detector_type.py
ome_types/_autogenerated/ome_2016_06/dichroic.py
ome_types/_autogenerated/ome_2016_06/dichroic_ref.py
ome_types/_autogenerated/ome_2016_06/double_annotation.py
ome_types/_autogenerated/ome_2016_06/ellipse.py
ome_types/_autogenerated/ome_2016_06/experiment.py
ome_types/_autogenerated/ome_2016_06/experiment_ref.py
ome_types/_autogenerated/ome_2016_06/experiment_value.py
ome_types/_autogenerated/ome_2016_06/experimenter.py
ome_types/_autogenerated/ome_2016_06/experimenter_group.py
ome_types-0.6.0.dist-info/METADATA
ome_types-0.6.0.dist-info/WHEEL
ome_types-0.6.0.dist-info/entry_points.txt
ome_types-0.6.0.dist-info/licenses/LICENSE
ome_types-0.6.0.dist-info/RECORD
