Metadata-Version: 2.4
Name: ome-types
Version: 0.6.0
Summary: Python dataclasses for the OME data model
Project-URL: Source, https://github.com/tlambert03/ome-types
Project-URL: Tracker, https://github.com/tlambert03/ome-types/issues
Project-URL: Documentation, https://ome-types.readthedocs.io/en/latest/
Author-email: Talley Lambert <talley.lambert@gmail.com>
License: MIT
License-File: LICENSE
Keywords: microscopy,ome,ome-model,schema,types
Classifier: Development Status :: 4 - Beta
Classifier: Intended Audience :: Developers
Classifier: Intended Audience :: Science/Research
Classifier: License :: OSI Approved :: MIT License
Classifier: Natural Language :: English
Classifier: Operating System :: OS Independent
Classifier: Programming Language :: Python
Classifier: Programming Language :: Python :: 3
Classifier: Programming Language :: Python :: 3.9
Classifier: Programming Language :: Python :: 3.10
Classifier: Programming Language :: Python :: 3.11
Classifier: Programming Language :: Python :: 3.12
Classifier: Programming Language :: Python :: 3.13
Requires-Python: >=3.9
Requires-Dist: pydantic-extra-types
Requires-Dist: pydantic>=2.4
Requires-Dist: xsdata<24.4,>=23.6
Provides-Extra: build
Requires-Dist: ruff==0.3.0; extra == 'build'
Requires-Dist: xsdata[cli]==24.2.1; extra == 'build'
Provides-Extra: dev
Requires-Dist: lxml; (python_version <= '3.12') and extra == 'dev'
Requires-Dist: mkdocs-material; extra == 'dev'
Requires-Dist: mkdocstrings-python; extra == 'dev'
Requires-Dist: mypy; extra == 'dev'
Requires-Dist: numpy; extra == 'dev'
Requires-Dist: pdbpp; (sys_platform != 'win32') and extra == 'dev'
Requires-Dist: pint; (python_version <= '3.12') and extra == 'dev'
Requires-Dist: pre-commit; extra == 'dev'
Requires-Dist: pytest; extra == 'dev'
Requires-Dist: pytest-codspeed; extra == 'dev'
Requires-Dist: pytest-cov; extra == 'dev'
Requires-Dist: pytest-mypy-plugins; extra == 'dev'
Requires-Dist: ruff; extra == 'dev'
Requires-Dist: ruff==0.3.0; extra == 'dev'
Requires-Dist: types-lxml; extra == 'dev'
Requires-Dist: xmlschema<2.5; extra == 'dev'
Requires-Dist: xsdata[cli]; extra == 'dev'
Requires-Dist: xsdata[cli]==24.2.1; extra == 'dev'
Provides-Extra: docs
Requires-Dist: mkdocs-material; extra == 'docs'
Requires-Dist: mkdocstrings-python; extra == 'docs'
Provides-Extra: lxml
Requires-Dist: lxml>=4.8.0; extra == 'lxml'
Provides-Extra: pint
Requires-Dist: pint>=0.15; extra == 'pint'
Provides-Extra: test
Requires-Dist: lxml; (python_version <= '3.12') and extra == 'test'
Requires-Dist: mypy; extra == 'test'
Requires-Dist: numpy; extra == 'test'
Requires-Dist: pdbpp; (sys_platform != 'win32') and extra == 'test'
Requires-Dist: pint; (python_version <= '3.12') and extra == 'test'
Requires-Dist: pytest; extra == 'test'
Requires-Dist: pytest-codspeed; extra == 'test'
Requires-Dist: pytest-cov; extra == 'test'
Requires-Dist: pytest-mypy-plugins; extra == 'test'
Requires-Dist: ruff; extra == 'test'
Requires-Dist: types-lxml; extra == 'test'
Requires-Dist: xmlschema<2.5; extra == 'test'
Requires-Dist: xsdata[cli]; extra == 'test'
Provides-Extra: test-qt
Requires-Dist: pytest-qt; extra == 'test-qt'
Requires-Dist: qtpy; extra == 'test-qt'
